{
  "OnInitSequece": [],
  "OnStartSequece": [
    {
      "IsLoop": true,
      "TaskList": [
        {
          "$type": "RPG.GameCore.WaitCustomString",
          "CustomString": {
            "Value": "ConsumeItem_301160501"
          },
          "GoNextImmediately": true
        },
        {
          "$type": "RPG.GameCore.SetNPCMonstersVisible",
          "TaskEnabled": true
        },
        {
          "$type": "RPG.GameCore.SelectMissionItem",
          "SubMissionID": 301160501,
          "OnlyPerformance": false,
          "ItemIDList": [
            401004,
            401012
          ],
          "ItemHiddenIDList": [],
          "ItemSelect": [
            {
              "Item1": 401004,
              "TriggerCustomString": "CMI_401004"
            },
            {
              "Item1": 401012,
              "TriggerCustomString": "CMI_401012"
            }
          ],
          "SlotNum": 1,
          "SimpleTalk": {}
        }
      ]
    }
  ]
}