{
  "GroupGUID": "77373427-e8a3-4e12-93b0-2d6da35852d6",
  "GroupName": "RogueDLC130_Area",
  "Category": "Custom",
  "AreaAnchorName": "LevelArea_P80204_F80204001_G21",
  "LoadSide": "Server",
  "LoadOnInitial": true,
  "ConflictIDList": [],
  "IsHoyoGroup": true,
  "ConflictSpatialInfo": {
    "CompactGridList": [],
    "LowerUpperBounds": {}
  },
  "StreamingSpatialInfo": {
    "CompactGridList": [
      -18,
      8,
      -12,
      24
    ],
    "LowerUpperBounds": {
      "x": 263,
      "y": 266
    }
  },
  "ConflictWhiteList": [],
  "AnchorList": [],
  "MonsterList": [],
  "PropList": [
    {
      "ID": 300001,
      "PosX": -22.28,
      "PosY": 2.700008,
      "PosZ": 49.71,
      "Name": "Prop1",
      "RotY": 270.0,
      "PropID": 1028,
      "IsOverrideInitLevelGraph": true,
      "CampID": 4,
      "MapLayerID": 1,
      "CustomTriggerMap": {},
      "CustomTriggerMapV2": {},
      "BridgeStateRotations": [],
      "DialogueGroups": [],
      "TalkDialogGroupIDList": [],
      "ServerInteractVerificationIDList": []
    },
    {
      "ID": 300002,
      "PosX": -35.25999,
      "PosY": -0.119205,
      "PosZ": 17.74,
      "Name": "Prop2",
      "Scale": {
        "x": 1.5,
        "y": 1.0,
        "z": 1.0
      },
      "PropID": 1028,
      "IsOverrideInitLevelGraph": true,
      "CampID": 4,
      "MapLayerID": 1,
      "CustomTriggerMap": {},
      "CustomTriggerMapV2": {},
      "BridgeStateRotations": [],
      "DialogueGroups": [],
      "TalkDialogGroupIDList": [],
      "ServerInteractVerificationIDList": []
    }
  ],
  "NPCList": []
}