{
  "OnInitSequece": [],
  "OnStartSequece": [
    {
      "TaskList": [
        {
          "$type": "RPG.GameCore.LevelPerformanceInitialize",
          "PerformanceType": "D",
          "CreateCharacterList": [],
          "EntityVisiableList": [],
          "PropVisiableList": [],
          "MarkStreamingItems": []
        },
        {
          "$type": "RPG.GameCore.AdvEnablePropDialogMode",
          "EnablePropCamera": false,
          "LockPlayerControl": false,
          "TargetType": {
            "$type": "RPG.GameCore.TargetFetchAdvPropEx",
            "FetchType": "SinglePropByPropID",
            "SinglePropID": {
              "GroupID": {
                "IsDynamic": false,
                "FixedValue": {
                  "Value": 95
                }
              },
              "ID": {
                "IsDynamic": false,
                "FixedValue": {
                  "Value": 300001
                }
              }
            }
          }
        },
        {
          "$type": "RPG.GameCore.PlayAndWaitSimpleTalk",
          "SimpleTalkList": [
            {
              "TalkSentenceID": 404121501,
              "ProtectTime": 0.3
            },
            {
              "TalkSentenceID": 404121502
            },
            {
              "TalkSentenceID": 404121503
            }
          ]
        },
        {
          "$type": "RPG.GameCore.TriggerCustomString",
          "CustomString": {
            "Value": "npccreate"
          }
        },
        {
          "$type": "RPG.GameCore.PlayAndWaitSimpleTalk",
          "BlackMask": true,
          "SimpleTalkList": [
            {
              "TalkSentenceID": 404121504,
              "ProtectTime": 0.3
            }
          ]
        },
        {
          "$type": "RPG.GameCore.AdvNpcFaceToPlayer",
          "GroupID": 95,
          "GroupNpcID": 400001,
          "FinishImmadiate": true
        },
        {
          "$type": "RPG.GameCore.PlayAndWaitSimpleTalk",
          "SimpleTalkList": [
            {
              "TalkSentenceID": 404121505,
              "ProtectTime": 0.3
            }
          ]
        },
        {
          "$type": "RPG.GameCore.PlayOptionTalk",
          "OptionList": [
            {
              "TalkSentenceID": 404121506,
              "OptionIconType": "ChatContinueIcon",
              "TriggerCustomString": "talksentence_404121506"
            },
            {
              "TalkSentenceID": 404121509,
              "OptionIconType": "ChatContinueIcon",
              "TriggerCustomString": "talksentence_404121509"
            },
            {
              "TalkSentenceID": 404121512,
              "OptionIconType": "ChatContinueIcon",
              "TriggerCustomString": "talksentence_404121512"
            }
          ]
        }
      ]
    },
    {
      "TaskList": [
        {
          "$type": "RPG.GameCore.WaitCustomString",
          "CustomString": {
            "Value": "npccreate"
          }
        },
        {
          "$type": "RPG.GameCore.CreateNPC",
          "GroupID": {
            "IsDynamic": false,
            "FixedValue": {
              "Value": 95
            }
          },
          "GroupNpcID": {
            "IsDynamic": false,
            "FixedValue": {
              "Value": 400001
            }
          }
        }
      ]
    },
    {
      "TaskList": [
        {
          "$type": "RPG.GameCore.WaitCustomString",
          "CustomString": {
            "Value": "talksentence_404121506"
          }
        },
        {
          "$type": "RPG.GameCore.PlayAndWaitSimpleTalk",
          "SimpleTalkList": [
            {
              "TalkSentenceID": 404121507,
              "ProtectTime": 0.3
            },
            {
              "TalkSentenceID": 404121508
            }
          ]
        },
        {
          "$type": "RPG.GameCore.TriggerCustomString",
          "CustomString": {
            "Value": "404121506_finish"
          }
        }
      ]
    },
    {
      "TaskList": [
        {
          "$type": "RPG.GameCore.WaitCustomString",
          "CustomString": {
            "Value": "talksentence_404121509"
          }
        },
        {
          "$type": "RPG.GameCore.PlayAndWaitSimpleTalk",
          "SimpleTalkList": [
            {
              "TalkSentenceID": 404121510,
              "ProtectTime": 0.3
            },
            {
              "TalkSentenceID": 404121511
            }
          ]
        },
        {
          "$type": "RPG.GameCore.TriggerCustomString",
          "CustomString": {
            "Value": "404121506_finish"
          }
        }
      ]
    },
    {
      "TaskList": [
        {
          "$type": "RPG.GameCore.WaitCustomString",
          "CustomString": {
            "Value": "talksentence_404121512"
          }
        },
        {
          "$type": "RPG.GameCore.PlayAndWaitSimpleTalk",
          "SimpleTalkList": [
            {
              "TalkSentenceID": 404121513,
              "ProtectTime": 0.3
            },
            {
              "TalkSentenceID": 404121514
            }
          ]
        },
        {
          "$type": "RPG.GameCore.TriggerCustomString",
          "CustomString": {
            "Value": "404121506_finish"
          }
        }
      ]
    },
    {
      "TaskList": [
        {
          "$type": "RPG.GameCore.WaitCustomString",
          "CustomString": {
            "Value": "404121506_finish"
          }
        },
        {
          "$type": "RPG.GameCore.PlayAndWaitSimpleTalk",
          "SimpleTalkList": [
            {
              "TalkSentenceID": 404121515,
              "ProtectTime": 0.3
            }
          ]
        },
        {
          "$type": "RPG.GameCore.PlayOptionTalk",
          "OptionList": [
            {
              "TalkSentenceID": 404121516,
              "OptionIconType": "ChatContinueIcon",
              "TriggerCustomString": "talksentence_404121516"
            },
            {
              "TalkSentenceID": 404121517,
              "OptionIconType": "ChatOutIcon",
              "TriggerCustomString": "stop_watching"
            }
          ]
        }
      ]
    },
    {
      "TaskList": [
        {
          "$type": "RPG.GameCore.WaitCustomString",
          "CustomString": {
            "Value": "talksentence_404121516"
          }
        },
        {
          "$type": "RPG.GameCore.PlayAndWaitSimpleTalk",
          "SimpleTalkList": [
            {
              "TalkSentenceID": 404121518,
              "ProtectTime": 0.3
            }
          ]
        },
        {
          "$type": "RPG.GameCore.PlayOptionTalk",
          "OptionList": [
            {
              "TalkSentenceID": 404121519,
              "OptionIconType": "ChatContinueIcon",
              "TriggerCustomString": "talksentence_404121519"
            },
            {
              "TalkSentenceID": 404121521,
              "OptionIconType": "ChatContinueIcon",
              "TriggerCustomString": "talksentence_404121521"
            },
            {
              "TalkSentenceID": 404121523,
              "OptionIconType": "ChatContinueIcon",
              "TriggerCustomString": "talksentence_404121523"
            }
          ]
        }
      ]
    },
    {
      "TaskList": [
        {
          "$type": "RPG.GameCore.WaitCustomString",
          "CustomString": {
            "Value": "talksentence_404121519"
          }
        },
        {
          "$type": "RPG.GameCore.PlayAndWaitSimpleTalk",
          "SimpleTalkList": [
            {
              "TalkSentenceID": 404121520,
              "ProtectTime": 0.3
            }
          ]
        },
        {
          "$type": "RPG.GameCore.TriggerCustomString",
          "CustomString": {
            "Value": "404121520_finish"
          }
        }
      ]
    },
    {
      "TaskList": [
        {
          "$type": "RPG.GameCore.WaitCustomString",
          "CustomString": {
            "Value": "talksentence_404121521"
          }
        },
        {
          "$type": "RPG.GameCore.PlayAndWaitSimpleTalk",
          "SimpleTalkList": [
            {
              "TalkSentenceID": 404121522,
              "ProtectTime": 0.3
            }
          ]
        },
        {
          "$type": "RPG.GameCore.TriggerCustomString",
          "CustomString": {
            "Value": "404121520_finish"
          }
        }
      ]
    },
    {
      "TaskList": [
        {
          "$type": "RPG.GameCore.WaitCustomString",
          "CustomString": {
            "Value": "talksentence_404121523"
          }
        },
        {
          "$type": "RPG.GameCore.PlayAndWaitSimpleTalk",
          "SimpleTalkList": [
            {
              "TalkSentenceID": 404121524,
              "ProtectTime": 0.3
            }
          ]
        },
        {
          "$type": "RPG.GameCore.TriggerCustomString",
          "CustomString": {
            "Value": "404121520_finish"
          }
        }
      ]
    },
    {
      "TaskList": [
        {
          "$type": "RPG.GameCore.WaitCustomString",
          "CustomString": {
            "Value": "404121520_finish"
          }
        },
        {
          "$type": "RPG.GameCore.PlayAndWaitSimpleTalk",
          "SimpleTalkList": [
            {
              "TalkSentenceID": 404121525,
              "ProtectTime": 0.3
            }
          ]
        },
        {
          "$type": "RPG.GameCore.PlayOptionTalk",
          "OptionList": [
            {
              "TalkSentenceID": 404121526,
              "OptionIconType": "ChatContinueIcon",
              "TriggerCustomString": "talksentence_404121526"
            },
            {
              "TalkSentenceID": 404121535,
              "OptionIconType": "ChatContinueIcon",
              "TriggerCustomString": "talksentence_404121535"
            },
            {
              "TalkSentenceID": 404121530,
              "OptionIconType": "ChatOutIcon",
              "TriggerCustomString": "talksentence_404121530"
            }
          ]
        }
      ]
    },
    {
      "TaskList": [
        {
          "$type": "RPG.GameCore.WaitCustomString",
          "CustomString": {
            "Value": "talksentence_404121526"
          }
        },
        {
          "$type": "RPG.GameCore.PlayAndWaitSimpleTalk",
          "SimpleTalkList": [
            {
              "TalkSentenceID": 404121527,
              "ProtectTime": 0.3
            }
          ]
        },
        {
          "$type": "RPG.GameCore.PlayAndWaitSimpleTalk",
          "BlackMask": true,
          "SimpleTalkList": [
            {
              "TalkSentenceID": 404121528,
              "ProtectTime": 0.3
            },
            {
              "TalkSentenceID": 404121529
            }
          ]
        },
        {
          "$type": "RPG.GameCore.SetMissionCustomValue",
          "SubmissionID": 404021501,
          "MissionCustomValue": {
            "ValidValueParamList": []
          },
          "CustomValue": 1
        },
        {
          "$type": "RPG.GameCore.TriggerCustomString",
          "CustomString": {
            "Value": "ALL_TALK_END"
          }
        }
      ]
    },
    {
      "TaskList": [
        {
          "$type": "RPG.GameCore.WaitCustomString",
          "CustomString": {
            "Value": "talksentence_404121530"
          }
        },
        {
          "$type": "RPG.GameCore.PlayAndWaitSimpleTalk",
          "SimpleTalkList": [
            {
              "TalkSentenceID": 404121531,
              "ProtectTime": 0.3
            },
            {
              "TalkSentenceID": 404121532
            },
            {
              "TalkSentenceID": 404121533
            },
            {
              "TalkSentenceID": 404121534
            }
          ]
        },
        {
          "$type": "RPG.GameCore.PlayAndWaitSimpleTalk",
          "SimpleTalkList": [
            {
              "TalkSentenceID": 404121572,
              "ProtectTime": 0.3
            }
          ]
        },
        {
          "$type": "RPG.GameCore.TriggerCustomString",
          "CustomString": {
            "Value": "stop_watching"
          }
        }
      ]
    },
    {
      "TaskList": [
        {
          "$type": "RPG.GameCore.WaitCustomString",
          "CustomString": {
            "Value": "talksentence_404121535"
          }
        },
        {
          "$type": "RPG.GameCore.PlayAndWaitSimpleTalk",
          "SimpleTalkList": [
            {
              "TalkSentenceID": 404121536,
              "ProtectTime": 0.3
            },
            {
              "TalkSentenceID": 404121537
            },
            {
              "TalkSentenceID": 404121538
            }
          ]
        },
        {
          "$type": "RPG.GameCore.PlayOptionTalk",
          "OptionList": [
            {
              "TalkSentenceID": 404121539,
              "OptionIconType": "ChatContinueIcon",
              "TriggerCustomString": "option_404121539_0"
            },
            {
              "TalkSentenceID": 404121541,
              "OptionIconType": "ChatContinueIcon",
              "TriggerCustomString": "option_404121541_0"
            },
            {
              "TalkSentenceID": 404121543,
              "OptionIconType": "ChatContinueIcon",
              "TriggerCustomString": "option_404121543"
            }
          ]
        }
      ]
    },
    {
      "TaskList": [
        {
          "$type": "RPG.GameCore.WaitCustomString",
          "CustomString": {
            "Value": "option_404121539_0"
          }
        },
        {
          "$type": "RPG.GameCore.PlayAndWaitSimpleTalk",
          "SimpleTalkList": [
            {
              "TalkSentenceID": 404121540,
              "ProtectTime": 0.3
            }
          ]
        },
        {
          "$type": "RPG.GameCore.PlayOptionTalk",
          "OptionList": [
            {
              "TalkSentenceID": 404121541,
              "OptionIconType": "ChatContinueIcon",
              "TriggerCustomString": "option_404121541_1"
            },
            {
              "TalkSentenceID": 404121543,
              "OptionIconType": "ChatContinueIcon",
              "TriggerCustomString": "option_404121543"
            }
          ]
        }
      ]
    },
    {
      "TaskList": [
        {
          "$type": "RPG.GameCore.WaitCustomString",
          "CustomString": {
            "Value": "option_404121541_1"
          }
        },
        {
          "$type": "RPG.GameCore.PlayAndWaitSimpleTalk",
          "SimpleTalkList": [
            {
              "TalkSentenceID": 404121542,
              "ProtectTime": 0.3
            }
          ]
        },
        {
          "$type": "RPG.GameCore.PlayOptionTalk",
          "OptionList": [
            {
              "TalkSentenceID": 404121543,
              "OptionIconType": "ChatContinueIcon",
              "TriggerCustomString": "option_404121543"
            }
          ]
        }
      ]
    },
    {
      "TaskList": [
        {
          "$type": "RPG.GameCore.WaitCustomString",
          "CustomString": {
            "Value": "option_404121541_0"
          }
        },
        {
          "$type": "RPG.GameCore.PlayAndWaitSimpleTalk",
          "SimpleTalkList": [
            {
              "TalkSentenceID": 404121542,
              "ProtectTime": 0.3
            }
          ]
        },
        {
          "$type": "RPG.GameCore.PlayOptionTalk",
          "OptionList": [
            {
              "TalkSentenceID": 404121539,
              "OptionIconType": "ChatContinueIcon",
              "TriggerCustomString": "option_404121539_1"
            },
            {
              "TalkSentenceID": 404121543,
              "OptionIconType": "ChatContinueIcon",
              "TriggerCustomString": "option_404121543"
            }
          ]
        }
      ]
    },
    {
      "TaskList": [
        {
          "$type": "RPG.GameCore.WaitCustomString",
          "CustomString": {
            "Value": "option_404121539_1"
          }
        },
        {
          "$type": "RPG.GameCore.PlayAndWaitSimpleTalk",
          "SimpleTalkList": [
            {
              "TalkSentenceID": 404121540,
              "ProtectTime": 0.3
            }
          ]
        },
        {
          "$type": "RPG.GameCore.PlayOptionTalk",
          "OptionList": [
            {
              "TalkSentenceID": 404121543,
              "OptionIconType": "ChatContinueIcon",
              "TriggerCustomString": "option_404121543"
            }
          ]
        }
      ]
    },
    {
      "TaskList": [
        {
          "$type": "RPG.GameCore.WaitCustomString",
          "CustomString": {
            "Value": "option_404121543"
          }
        },
        {
          "$type": "RPG.GameCore.PlayAndWaitSimpleTalk",
          "SimpleTalkList": [
            {
              "TalkSentenceID": 404121544,
              "ProtectTime": 0.3
            },
            {
              "TalkSentenceID": 404121545
            },
            {
              "TalkSentenceID": 404121546
            }
          ]
        },
        {
          "$type": "RPG.GameCore.PlayAndWaitSimpleTalk",
          "SimpleTalkList": [
            {
              "TalkSentenceID": 404121547
            }
          ]
        },
        {
          "$type": "RPG.GameCore.TriggerCustomString",
          "CustomString": {
            "Value": "talksentence_404121547"
          }
        }
      ]
    },
    {
      "TaskList": [
        {
          "$type": "RPG.GameCore.WaitCustomString",
          "CustomString": {
            "Value": "talksentence_404121547"
          }
        },
        {
          "$type": "RPG.GameCore.PlayAndWaitSimpleTalk",
          "BlackMask": true,
          "SimpleTalkList": [
            {
              "TalkSentenceID": 404121548,
              "ProtectTime": 0.3
            }
          ]
        },
        {
          "$type": "RPG.GameCore.PlayOptionTalk",
          "OptionList": [
            {
              "TalkSentenceID": 404121549,
              "OptionIconType": "ChatContinueIcon",
              "TriggerCustomString": "option_404121549"
            },
            {
              "TalkSentenceID": 404121552,
              "OptionIconType": "ChatContinueIcon",
              "TriggerCustomString": "option_404121552"
            },
            {
              "TalkSentenceID": 404121555,
              "OptionIconType": "ChatContinueIcon",
              "TriggerCustomString": "option_404121555"
            }
          ]
        }
      ]
    },
    {
      "TaskList": [
        {
          "$type": "RPG.GameCore.WaitCustomString",
          "CustomString": {
            "Value": "option_404121549"
          }
        },
        {
          "$type": "RPG.GameCore.PlayAndWaitSimpleTalk",
          "BlackMask": true,
          "SimpleTalkList": [
            {
              "TalkSentenceID": 404121550,
              "ProtectTime": 0.3
            },
            {
              "TalkSentenceID": 404121551
            }
          ]
        },
        {
          "$type": "RPG.GameCore.SetMissionCustomValue",
          "SubmissionID": 404021501,
          "MissionCustomValue": {
            "ValidValueParamList": []
          },
          "CustomValue": 2
        },
        {
          "$type": "RPG.GameCore.TriggerCustomString",
          "CustomString": {
            "Value": "ALL_TALK_END"
          }
        }
      ]
    },
    {
      "TaskList": [
        {
          "$type": "RPG.GameCore.WaitCustomString",
          "CustomString": {
            "Value": "option_404121552"
          }
        },
        {
          "$type": "RPG.GameCore.PlayAndWaitSimpleTalk",
          "BlackMask": true,
          "SimpleTalkList": [
            {
              "TalkSentenceID": 404121553,
              "ProtectTime": 0.3
            },
            {
              "TalkSentenceID": 404121554
            }
          ]
        },
        {
          "$type": "RPG.GameCore.SetMissionCustomValue",
          "SubmissionID": 404021501,
          "MissionCustomValue": {
            "ValidValueParamList": []
          },
          "CustomValue": 2
        },
        {
          "$type": "RPG.GameCore.TriggerCustomString",
          "CustomString": {
            "Value": "ALL_TALK_END"
          }
        }
      ]
    },
    {
      "TaskList": [
        {
          "$type": "RPG.GameCore.WaitCustomString",
          "CustomString": {
            "Value": "option_404121555"
          }
        },
        {
          "$type": "RPG.GameCore.PlayAndWaitSimpleTalk",
          "BlackMask": true,
          "SimpleTalkList": [
            {
              "TalkSentenceID": 404121557,
              "ProtectTime": 0.3
            },
            {
              "TalkSentenceID": 404121558
            }
          ]
        },
        {
          "$type": "RPG.GameCore.SetMissionCustomValue",
          "SubmissionID": 404021501,
          "MissionCustomValue": {
            "ValidValueParamList": []
          },
          "CustomValue": 2
        },
        {
          "$type": "RPG.GameCore.TriggerCustomString",
          "CustomString": {
            "Value": "ALL_TALK_END"
          }
        }
      ]
    },
    {
      "TaskList": [
        {
          "$type": "RPG.GameCore.WaitCustomString",
          "CustomString": {
            "Value": "ALL_TALK_END"
          }
        },
        {
          "$type": "RPG.GameCore.TriggerCustomString",
          "CustomString": {
            "Value": "404021501_Finish"
          }
        },
        {
          "$type": "RPG.GameCore.EndPerformance"
        }
      ]
    },
    {
      "TaskList": [
        {
          "$type": "RPG.GameCore.WaitCustomString",
          "CustomString": {
            "Value": "stop_watching"
          }
        },
        {
          "$type": "RPG.GameCore.PerformanceTransition",
          "CreateNpcList": [],
          "CaptureNpcList": [],
          "DestroyNpcList": [
            {
              "GroupID": 95,
              "GroupNpcID": 400001,
              "DestroyList": []
            }
          ],
          "ActiveVirtualCamera": {
            "TaskEnabled": false
          },
          "SwitchCharacterAnchor": {
            "TaskEnabled": false
          }
        },
        {
          "$type": "RPG.GameCore.EndPerformance"
        }
      ]
    },
    {
      "TaskList": [
        {
          "$type": "RPG.GameCore.WaitPerformanceEnd"
        },
        {
          "$type": "RPG.GameCore.FinishLevelGraph"
        }
      ]
    }
  ]
}