{
  "GroupGUID": "bbe61d9e-04cc-40fe-9653-1fae2964fe48",
  "GroupName": "HideArea02",
  "AreaAnchorName": "LevelArea_P40122_F40122001_G13",
  "SaveType": "Reset",
  "LoadCondition": {
    "Conditions": [
      {
        "Type": "SubMission",
        "Phase": "Finish",
        "ID": 201180102
      }
    ]
  },
  "UnloadCondition": {
    "Conditions": [
      {
        "Type": "SubMission",
        "Phase": "Finish",
        "ID": 201180105
      }
    ]
  },
  "GroupStateList": [],
  "ConflictIDList": [],
  "AnchorList": [
    {
      "ID": 1,
      "PosX": -10.45,
      "PosY": 1.091492,
      "PosZ": 157.68,
      "Name": "Anchor1",
      "RotY": 287.9047,
      "MapLayerID": 1
    },
    {
      "ID": 2,
      "PosX": -8.689999,
      "PosY": 1.080284,
      "PosZ": 160.59,
      "Name": "Anchor2",
      "RotY": 351.0,
      "MapLayerID": 1
    },
    {
      "ID": 3,
      "PosX": -7.88,
      "PosY": 1.045594,
      "PosZ": 166.95,
      "Name": "Anchor3",
      "RotY": 305.0,
      "MapLayerID": 1
    },
    {
      "ID": 6,
      "PosX": -39.268,
      "PosY": 9.07466,
      "PosZ": 161.889,
      "Name": "Anchor6",
      "RotY": 102.5428,
      "MapLayerID": 1
    },
    {
      "ID": 7,
      "PosX": -26.567,
      "PosY": 4.884806,
      "PosZ": 170.508,
      "Name": "Anchor7",
      "RotY": 180.0,
      "MapLayerID": 1
    },
    {
      "ID": 4,
      "PosX": -16.628,
      "PosY": 1.022944,
      "PosZ": 165.259,
      "Name": "Anchor4",
      "RotY": 330.0,
      "MapLayerID": 1
    },
    {
      "ID": 5,
      "PosX": -47.971,
      "PosY": 13.47,
      "PosZ": 151.94,
      "Name": "Anchor5",
      "MapLayerID": 2
    },
    {
      "ID": 8,
      "PosX": -33.37,
      "PosY": 9.074661,
      "PosZ": 154.35,
      "Name": "Anchor8",
      "RotY": 270.0,
      "MapLayerID": 1
    }
  ],
  "MonsterList": [],
  "PropList": [
    {
      "ID": 300002,
      "PosX": -10.45,
      "PosY": 1.091492,
      "PosZ": 157.68,
      "Name": "HiddenProp1",
      "RotY": 72.69345,
      "PropID": 136,
      "IsOverrideInitLevelGraph": true,
      "InitLevelGraph": "Config/Level/Raid/TrackGamePlay/HiddenProp.json",
      "ValueSource": {
        "Values": [
          {
            "$type": "SharedString",
            "Key": "HiddenAnchor",
            "Value": "LevelArea_P40122_F40122001_G13,Anchor1"
          },
          {
            "$type": "SharedString",
            "Key": "LookAtTarget",
            "Value": "10,400001"
          },
          {
            "$type": "SharedString",
            "Key": "TriggerNPCTrackVisionOff",
            "Value": "TriggerNPCTrackVisionOff"
          },
          {
            "$type": "SharedString",
            "Key": "TriggerNPCTrackVisionOn",
            "Value": "TriggerNPCTrackVisionOn"
          },
          {
            "$type": "SharedString",
            "Key": "Track_OnFail_Reset",
            "Value": "Track_OnFail_Reset01"
          }
        ]
      },
      "CampID": 4,
      "MapLayerID": 1,
      "CustomTriggerMap": {},
      "BridgeStateRotations": [],
      "DialogueGroups": [],
      "TalkDialogGroupIDList": [],
      "ServerInteractVerificationIDList": []
    },
    {
      "ID": 300003,
      "PosX": -8.689999,
      "PosY": 1.080284,
      "PosZ": 160.59,
      "Name": "HiddenProp2",
      "RotY": 21.0,
      "PropID": 136,
      "IsOverrideInitLevelGraph": true,
      "InitLevelGraph": "Config/Level/Raid/TrackGamePlay/HiddenProp.json",
      "ValueSource": {
        "Values": [
          {
            "$type": "SharedString",
            "Key": "HiddenAnchor",
            "Value": "LevelArea_P40122_F40122001_G13,Anchor2"
          },
          {
            "$type": "SharedString",
            "Key": "LookAtTarget",
            "Value": "10,400001"
          },
          {
            "$type": "SharedString",
            "Key": "TriggerNPCTrackVisionOff",
            "Value": "TriggerNPCTrackVisionOff"
          },
          {
            "$type": "SharedString",
            "Key": "TriggerNPCTrackVisionOn",
            "Value": "TriggerNPCTrackVisionOn"
          },
          {
            "$type": "SharedString",
            "Key": "PositionSelection",
            "Value": "Left"
          },
          {
            "$type": "SharedString",
            "Key": "Track_OnFail_Reset",
            "Value": "Track_OnFail_Reset01"
          }
        ]
      },
      "MapLayerID": 1,
      "CustomTriggerMap": {},
      "BridgeStateRotations": [],
      "DialogueGroups": [],
      "TalkDialogGroupIDList": [],
      "ServerInteractVerificationIDList": []
    },
    {
      "ID": 300004,
      "PosX": -7.88,
      "PosY": 1.045594,
      "PosZ": 166.95,
      "Name": "HiddenProp3",
      "RotY": 65.00001,
      "PropID": 136,
      "IsOverrideInitLevelGraph": true,
      "InitLevelGraph": "Config/Level/Raid/TrackGamePlay/HiddenProp.json",
      "ValueSource": {
        "Values": [
          {
            "$type": "SharedString",
            "Key": "HiddenAnchor",
            "Value": "LevelArea_P40122_F40122001_G13,Anchor3"
          },
          {
            "$type": "SharedString",
            "Key": "LookAtTarget",
            "Value": "10,400001"
          },
          {
            "$type": "SharedString",
            "Key": "TriggerNPCTrackVisionOff",
            "Value": "TriggerNPCTrackVisionOff"
          },
          {
            "$type": "SharedString",
            "Key": "TriggerNPCTrackVisionOn",
            "Value": "TriggerNPCTrackVisionOn"
          },
          {
            "$type": "SharedString",
            "Key": "PositionSelection",
            "Value": "Left"
          },
          {
            "$type": "SharedString",
            "Key": "Track_OnFail_Reset",
            "Value": "Track_OnFail_Reset01"
          }
        ]
      },
      "CampID": 4,
      "MapLayerID": 1,
      "CustomTriggerMap": {},
      "BridgeStateRotations": [],
      "DialogueGroups": [],
      "TalkDialogGroupIDList": [],
      "ServerInteractVerificationIDList": []
    },
    {
      "ID": 300007,
      "PosX": -39.268,
      "PosY": 9.07466,
      "PosZ": 161.889,
      "Name": "HiddenProp6",
      "RotY": 312.5428,
      "PropID": 136,
      "IsOverrideInitLevelGraph": true,
      "InitLevelGraph": "Config/Level/Raid/TrackGamePlay/HiddenProp.json",
      "ValueSource": {
        "Values": [
          {
            "$type": "SharedString",
            "Key": "HiddenAnchor",
            "Value": "LevelArea_P40122_F40122001_G13,Anchor6"
          },
          {
            "$type": "SharedString",
            "Key": "LookAtTarget",
            "Value": "10,400001"
          },
          {
            "$type": "SharedString",
            "Key": "TriggerNPCTrackVisionOff",
            "Value": "TriggerNPCTrackVisionOff"
          },
          {
            "$type": "SharedString",
            "Key": "TriggerNPCTrackVisionOn",
            "Value": "TriggerNPCTrackVisionOn"
          },
          {
            "$type": "SharedString",
            "Key": "PositionSelection",
            "Value": "Right"
          },
          {
            "$type": "SharedString",
            "Key": "Track_OnFail_Reset",
            "Value": "Track_OnFail_Reset01"
          }
        ]
      },
      "CampID": 4,
      "MapLayerID": 1,
      "CustomTriggerMap": {},
      "BridgeStateRotations": [],
      "DialogueGroups": [],
      "TalkDialogGroupIDList": [],
      "ServerInteractVerificationIDList": []
    },
    {
      "ID": 300008,
      "PosX": -26.567,
      "PosY": 4.884806,
      "PosZ": 170.508,
      "Name": "HiddenProp7",
      "RotY": 180.0,
      "PropID": 136,
      "IsOverrideInitLevelGraph": true,
      "InitLevelGraph": "Config/Level/Raid/TrackGamePlay/HiddenProp.json",
      "ValueSource": {
        "Values": [
          {
            "$type": "SharedString",
            "Key": "HiddenAnchor",
            "Value": "LevelArea_P40122_F40122001_G13,Anchor7"
          },
          {
            "$type": "SharedString",
            "Key": "LookAtTarget",
            "Value": "10,400001"
          },
          {
            "$type": "SharedString",
            "Key": "TriggerNPCTrackVisionOff",
            "Value": "TriggerNPCTrackVisionOff"
          },
          {
            "$type": "SharedString",
            "Key": "TriggerNPCTrackVisionOn",
            "Value": "TriggerNPCTrackVisionOn"
          },
          {
            "$type": "SharedString",
            "Key": "PositionSelection",
            "Value": "Right"
          },
          {
            "$type": "SharedString",
            "Key": "Track_OnFail_Reset",
            "Value": "Track_OnFail_Reset01"
          }
        ]
      },
      "CampID": 4,
      "MapLayerID": 1,
      "CustomTriggerMap": {},
      "BridgeStateRotations": [],
      "DialogueGroups": [],
      "TalkDialogGroupIDList": [],
      "ServerInteractVerificationIDList": []
    },
    {
      "ID": 300001,
      "PosX": -16.628,
      "PosY": 1.022944,
      "PosZ": 165.259,
      "Name": "HiddenProp2",
      "PropID": 136,
      "IsOverrideInitLevelGraph": true,
      "InitLevelGraph": "Config/Level/Raid/TrackGamePlay/HiddenProp.json",
      "ValueSource": {
        "Values": [
          {
            "$type": "SharedString",
            "Key": "HiddenAnchor",
            "Value": "LevelArea_P40122_F40122001_G13,Anchor4"
          },
          {
            "$type": "SharedString",
            "Key": "LookAtTarget",
            "Value": "10,400001"
          },
          {
            "$type": "SharedString",
            "Key": "TriggerNPCTrackVisionOff",
            "Value": "TriggerNPCTrackVisionOff"
          },
          {
            "$type": "SharedString",
            "Key": "TriggerNPCTrackVisionOn",
            "Value": "TriggerNPCTrackVisionOn"
          },
          {
            "$type": "SharedString",
            "Key": "PositionSelection",
            "Value": "Left"
          },
          {
            "$type": "SharedString",
            "Key": "Track_OnFail_Reset",
            "Value": "Track_OnFail_Reset01"
          }
        ]
      },
      "MapLayerID": 1,
      "CustomTriggerMap": {},
      "BridgeStateRotations": [],
      "DialogueGroups": [],
      "TalkDialogGroupIDList": [],
      "ServerInteractVerificationIDList": []
    },
    {
      "ID": 300005,
      "PosX": -10.85,
      "PosY": 1.02997,
      "PosZ": 159.01,
      "Name": "SoundTrigger",
      "RotY": 346.5835,
      "PropID": 100,
      "IsOverrideInitLevelGraph": true,
      "InitLevelGraph": "Config/Level/Raid/TrackGamePlay/TrackNpcTriggerSound.json",
      "ValueSource": {
        "Values": [
          {
            "$type": "SharedString",
            "Key": "Track_OnFail_Reset",
            "Value": "Track_OnFail_Reset01"
          }
        ]
      },
      "Trigger": {
        "Shape": "Box",
        "Radius": 2.0,
        "DimX": 10.0,
        "DimY": 1.0,
        "DimZ": 1.0,
        "Offset": {
          "x": -4.0
        },
        "PointList": []
      },
      "CampID": 4,
      "MapLayerID": 1,
      "CustomTriggerMap": {},
      "BridgeStateRotations": [],
      "DialogueGroups": [],
      "TalkDialogGroupIDList": [],
      "ServerInteractVerificationIDList": []
    },
    {
      "ID": 300006,
      "PosX": -47.971,
      "PosY": 13.47,
      "PosZ": 151.94,
      "Name": "HiddenProp1",
      "RotY": 22.30113,
      "PropID": 136,
      "IsOverrideInitLevelGraph": true,
      "InitLevelGraph": "Config/Level/Raid/TrackGamePlay/HiddenProp.json",
      "ValueSource": {
        "Values": [
          {
            "$type": "SharedString",
            "Key": "HiddenAnchor",
            "Value": "LevelArea_P40122_F40122001_G13,Anchor5"
          },
          {
            "$type": "SharedString",
            "Key": "LookAtTarget",
            "Value": "10,400001"
          },
          {
            "$type": "SharedString",
            "Key": "TriggerNPCTrackVisionOff",
            "Value": "TriggerNPCTrackVisionOff"
          },
          {
            "$type": "SharedString",
            "Key": "TriggerNPCTrackVisionOn",
            "Value": "TriggerNPCTrackVisionOn"
          },
          {
            "$type": "SharedString",
            "Key": "PositionSelection",
            "Value": "Right"
          },
          {
            "$type": "SharedString",
            "Key": "Track_OnFail_Reset",
            "Value": "Track_OnFail_Reset01"
          }
        ]
      },
      "CampID": 4,
      "MapLayerID": 2,
      "CustomTriggerMap": {},
      "BridgeStateRotations": [],
      "DialogueGroups": [],
      "TalkDialogGroupIDList": [],
      "ServerInteractVerificationIDList": []
    },
    {
      "ID": 300009,
      "PosX": -33.37,
      "PosY": 9.074661,
      "PosZ": 154.35,
      "Name": "HiddenProp1",
      "RotY": 37.63,
      "PropID": 136,
      "IsOverrideInitLevelGraph": true,
      "InitLevelGraph": "Config/Level/Raid/TrackGamePlay/HiddenProp.json",
      "ValueSource": {
        "Values": [
          {
            "$type": "SharedString",
            "Key": "HiddenAnchor",
            "Value": "LevelArea_P40122_F40122001_G13,Anchor8"
          },
          {
            "$type": "SharedString",
            "Key": "LookAtTarget",
            "Value": "10,400001"
          },
          {
            "$type": "SharedString",
            "Key": "TriggerNPCTrackVisionOff",
            "Value": "TriggerNPCTrackVisionOff"
          },
          {
            "$type": "SharedString",
            "Key": "TriggerNPCTrackVisionOn",
            "Value": "TriggerNPCTrackVisionOn"
          },
          {
            "$type": "SharedString",
            "Key": "Track_OnFail_Reset",
            "Value": "Track_OnFail_Reset01"
          }
        ]
      },
      "CampID": 4,
      "MapLayerID": 1,
      "CustomTriggerMap": {
        "CustomTrigger_ShowEffect": {
          "Radius": 8.0,
          "PointList": []
        }
      },
      "BridgeStateRotations": [],
      "DialogueGroups": [],
      "TalkDialogGroupIDList": [],
      "ServerInteractVerificationIDList": []
    }
  ],
  "NPCList": []
}