{
  "AbilityList": [
    {
      "Modifiers": {
        "MStrongChallengeEX_MonsterTag_BOSS_1001": {
          "_CallbackList": [
            {
              "Event": "OnStack",
              "CallbackConfig": [
                {
                  "$type": "RPG.GameCore.AddModifier",
                  "TargetType": {
                    "$type": "RPG.GameCore.TargetAlias",
                    "Alias": "Caster"
                  },
                  "ModifierName": "Monster_IF_BOSS_Common_BreakBonus"
                }
              ]
            },
            {
              "Event": "OnListenCharacterCreate",
              "CallbackConfig": [
                {
                  "$type": "RPG.GameCore.PredicateTaskList",
                  "Predicate": {
                    "$type": "RPG.GameCore.ByAnd",
                    "PredicateList": [
                      {
                        "$type": "RPG.GameCore.ByTargetTeam",
                        "TargetType": {
                          "$type": "RPG.GameCore.TargetAlias",
                          "Alias": "ParamEntity"
                        },
                        "Team": "TeamDark"
                      },
                      {
                        "$type": "RPG.GameCore.ByCompareMonsterRank",
                        "TargetType": {
                          "$type": "RPG.GameCore.TargetAlias",
                          "Alias": "ParamEntity"
                        },
                        "CompareType": "GreaterEqual",
                        "CompareValue": 4
                      }
                    ]
                  },
                  "SuccessTaskList": [
                    {
                      "$type": "RPG.GameCore.AddModifier",
                      "TargetType": {
                        "$type": "RPG.GameCore.TargetAlias",
                        "Alias": "ParamEntity"
                      },
                      "ModifierName": "Monster_IF_BOSS_Common_BreakBonus"
                    }
                  ]
                }
              ]
            }
          ]
        }
      },
      "Name": "StrongChallengeEX_MonsterTag_1001",
      "OnAdd": [
        {
          "$type": "RPG.GameCore.AddModifier",
          "TargetType": {
            "$type": "RPG.GameCore.TargetAlias",
            "Alias": "Caster"
          },
          "ModifierName": "MStrongChallengeEX_MonsterTag_BOSS_1001"
        }
      ]
    },
    {
      "Modifiers": {
        "MStrongChallengeEX_MonsterTag_BOSS_2011": {}
      },
      "Name": "StrongChallengeEX_MonsterTag_2011",
      "OnAdd": [
        {
          "$type": "RPG.GameCore.AddModifier",
          "TargetType": {
            "$type": "RPG.GameCore.TargetAlias",
            "Alias": "Caster"
          },
          "ModifierName": "MStrongChallengeEX_MonsterTag_BOSS_2011"
        }
      ]
    },
    {
      "Modifiers": {
        "MStrongChallengeEX_MonsterTag_BOSS_2012": {}
      },
      "Name": "StrongChallengeEX_MonsterTag_2012",
      "OnAdd": [
        {
          "$type": "RPG.GameCore.AddModifier",
          "TargetType": {
            "$type": "RPG.GameCore.TargetAlias",
            "Alias": "Caster"
          },
          "ModifierName": "MStrongChallengeEX_MonsterTag_BOSS_2012"
        }
      ]
    },
    {
      "Modifiers": {
        "MStrongChallengeEX_MonsterTag_BOSS_2013": {}
      },
      "Name": "StrongChallengeEX_MonsterTag_2013",
      "OnAdd": [
        {
          "$type": "RPG.GameCore.AddModifier",
          "TargetType": {
            "$type": "RPG.GameCore.TargetAlias",
            "Alias": "Caster"
          },
          "ModifierName": "MStrongChallengeEX_MonsterTag_BOSS_2013"
        }
      ]
    },
    {
      "Modifiers": {
        "MStrongChallengeEX_MonsterTag_BOSS_2021": {}
      },
      "Name": "StrongChallengeEX_MonsterTag_2021",
      "OnAdd": [
        {
          "$type": "RPG.GameCore.AddModifier",
          "TargetType": {
            "$type": "RPG.GameCore.TargetAlias",
            "Alias": "Caster"
          },
          "ModifierName": "MStrongChallengeEX_MonsterTag_BOSS_2021"
        }
      ]
    },
    {
      "Modifiers": {
        "MStrongChallengeEX_MonsterTag_BOSS_2022": {}
      },
      "Name": "StrongChallengeEX_MonsterTag_2022",
      "OnAdd": [
        {
          "$type": "RPG.GameCore.AddModifier",
          "TargetType": {
            "$type": "RPG.GameCore.TargetAlias",
            "Alias": "Caster"
          },
          "ModifierName": "MStrongChallengeEX_MonsterTag_BOSS_2022"
        }
      ]
    },
    {
      "Modifiers": {
        "MStrongChallengeEX_MonsterTag_BOSS_2023": {}
      },
      "Name": "StrongChallengeEX_MonsterTag_2023",
      "OnAdd": [
        {
          "$type": "RPG.GameCore.AddModifier",
          "TargetType": {
            "$type": "RPG.GameCore.TargetAlias",
            "Alias": "Caster"
          },
          "ModifierName": "MStrongChallengeEX_MonsterTag_BOSS_2023"
        }
      ]
    }
  ],
  "GlobalModifiers": {}
}