{
  "OnInitSequece": [],
  "OnStartSequece": [
    {
      "TaskList": [
        {
          "$type": "RPG.GameCore.LevelPerformanceInitialize",
          "PerformanceType": "E",
          "CreateCharacterList": [],
          "EntityVisiableList": [],
          "HideMunicipalCrowd": false,
          "HideMunicipalPedestrian": false,
          "HideMunicipalOther": false,
          "PropVisiableList": [],
          "MarkStreamingItems": []
        },
        {
          "$type": "RPG.GameCore.AdvNpcFaceToPlayer",
          "FromDialog": false,
          "GroupID": 104,
          "GroupNpcID": 400001,
          "FinishImmadiate": true
        },
        {
          "$type": "RPG.GameCore.PlayAndWaitSimpleTalk",
          "SimpleTalkList": [
            {
              "TalkSentenceID": 405200201,
              "ProtectTime": 0.3
            },
            {
              "TalkSentenceID": 405200202,
              "ProtectTime": 0.3
            }
          ]
        },
        {
          "$type": "RPG.GameCore.PlayOptionTalk",
          "OptionList": [
            {
              "TalkSentenceID": 405200203,
              "OptionIconType": "ChatContinueIcon",
              "TriggerCustomString": "TalkSentence_405200204"
            }
          ]
        }
      ]
    },
    {
      "TaskList": [
        {
          "$type": "RPG.GameCore.WaitCustomString",
          "CustomString": {
            "Value": "TalkSentence_405200204"
          }
        },
        {
          "$type": "RPG.GameCore.PlayAndWaitSimpleTalk",
          "SimpleTalkList": [
            {
              "TalkSentenceID": 405200204,
              "ProtectTime": 0.3
            },
            {
              "TalkSentenceID": 405200205,
              "ProtectTime": 0.3
            }
          ]
        },
        {
          "$type": "RPG.GameCore.EndPerformance"
        }
      ]
    },
    {
      "TaskList": [
        {
          "$type": "RPG.GameCore.WaitPerformanceEnd"
        },
        {
          "$type": "RPG.GameCore.FinishLevelGraph"
        }
      ]
    }
  ]
}