{
  "GroupGUID": "c657f2d5-62d3-4711-9ef9-915d0bfebefd",
  "GroupName": "Rogue_NormalRoom",
  "LevelGraph": "Config/Level/Maze/MazeRogue/Maze_Rogue_Group_NormalRoom.json",
  "AreaAnchorName": "LevelArea_P81111_F81111001_G85",
  "LoadSide": "Server",
  "AnchorList": [
    {
      "ID": 1,
      "PosX": 20.86,
      "PosY": -2.133952,
      "PosZ": -170.24,
      "Name": "Anchor1",
      "RotY": 270.0,
      "MapLayerID": 1
    }
  ],
  "MonsterList": [
    {
      "ID": 200005,
      "PosX": 4.34,
      "PosY": -2.133952,
      "PosZ": -171.37,
      "Name": "Monster5",
      "RotY": 89.99994,
      "NPCMonsterID": 1002040,
      "AIConfig": {
        "PathwayList": [],
        "SlaveConfigList": []
      },
      "CampID": 3,
      "BattleArea": {
        "GroupID": 1,
        "ID": 1
      },
      "MapLayerID": 1,
      "BoardShowList": [
        4
      ]
    }
  ],
  "PropList": [
    {
      "ID": 300001,
      "PosX": -34.51,
      "PosY": -2.133952,
      "PosZ": -172.21,
      "Name": "Buff",
      "RotY": 90.0,
      "PropID": 100,
      "IsOverrideInitLevelGraph": true,
      "InitLevelGraph": "Config/Level/Maze/MazeRogue/Maze_Rogue_Prop_TriggerBuffSelect.json",
      "Trigger": {
        "Radius": 2.0,
        "DimX": 1.0,
        "DimY": 1.0,
        "DimZ": 1.0
      },
      "CampID": 4,
      "MapLayerID": 1,
      "CustomTriggerMap": {},
      "BridgeStateRotations": [],
      "DialogueGroups": [],
      "TalkDialogGroupIDList": [],
      "ServerInteractVerificationIDList": []
    },
    {
      "ID": 300002,
      "PosX": 1.29,
      "PosY": -2.133952,
      "PosZ": -172.34,
      "Name": "Door1",
      "RotY": 75.00016,
      "PropID": 1000,
      "IsOverrideInitLevelGraph": true,
      "InitLevelGraph": "Config/Level/Maze/MazeRogue/Maze_Rogue_Prop_Door.json",
      "Trigger": {
        "Radius": 2.0,
        "DimX": 1.0,
        "DimY": 1.0,
        "DimZ": 1.0
      },
      "CampID": 4,
      "MapLayerID": 1,
      "CustomTriggerMap": {
        "CustomTrigger_DoorOpen": {
          "Radius": 3.5
        }
      },
      "BridgeStateRotations": [],
      "DialogueGroups": [],
      "TalkDialogGroupIDList": [],
      "ServerInteractVerificationIDList": []
    },
    {
      "ID": 300006,
      "PosX": 13.70271,
      "PosY": -2.106081,
      "PosZ": -174.4868,
      "Name": "Destruct",
      "RotY": 90.0,
      "PropID": 101017,
      "IsOverrideInitLevelGraph": true,
      "CampID": 4,
      "EventID": 80210001,
      "MapLayerID": 1,
      "CustomTriggerMap": {},
      "BridgeStateRotations": [],
      "DialogueGroups": [],
      "TalkDialogGroupIDList": [],
      "ServerInteractVerificationIDList": []
    },
    {
      "ID": 300004,
      "PosX": 1.49,
      "PosY": -2.133952,
      "PosZ": -168.0,
      "Name": "Door2",
      "RotY": 105.0,
      "PropID": 1000,
      "IsOverrideInitLevelGraph": true,
      "InitLevelGraph": "Config/Level/Maze/MazeRogue/Maze_Rogue_Prop_Door.json",
      "Trigger": {
        "Radius": 2.0,
        "DimX": 1.0,
        "DimY": 1.0,
        "DimZ": 1.0
      },
      "CampID": 4,
      "MapLayerID": 1,
      "CustomTriggerMap": {
        "CustomTrigger_DoorOpen": {
          "Radius": 3.5
        }
      },
      "BridgeStateRotations": [],
      "DialogueGroups": [],
      "TalkDialogGroupIDList": [],
      "ServerInteractVerificationIDList": []
    },
    {
      "ID": 300003,
      "PosX": 10.2,
      "PosY": -2.133952,
      "PosZ": -161.86,
      "Name": "Destruct",
      "RotY": 135.0,
      "PropID": 101017,
      "IsOverrideInitLevelGraph": true,
      "CampID": 4,
      "EventID": 80210001,
      "MapLayerID": 1,
      "CustomTriggerMap": {},
      "BridgeStateRotations": [],
      "DialogueGroups": [],
      "TalkDialogGroupIDList": [],
      "ServerInteractVerificationIDList": []
    },
    {
      "ID": 300005,
      "PosX": 1.273,
      "PosY": -2.133952,
      "PosZ": -170.282,
      "Name": "Prop5",
      "RotY": 89.99994,
      "PropID": 100,
      "IsOverrideInitLevelGraph": true,
      "InitLevelGraph": "Config/Level/Maze/MazeRogueV3/Maze_Rogue_Prop_ElitHint.json",
      "CampID": 4,
      "MapLayerID": 1,
      "CustomTriggerMap": {},
      "BridgeStateRotations": [],
      "DialogueGroups": [],
      "TalkDialogGroupIDList": [],
      "ServerInteractVerificationIDList": [],
      "OverrideMapStateIcons": [
        {
          "IconID": 6
        }
      ]
    },
    {
      "ID": 300007,
      "PosX": 4.309,
      "PosY": -2.133952,
      "PosZ": -175.128,
      "Name": "Prop7",
      "RotY": 7.7E-5,
      "PropID": 105,
      "IsOverrideInitLevelGraph": true,
      "CampID": 4,
      "MapLayerID": 1,
      "CustomTriggerMap": {},
      "BridgeStateRotations": [],
      "DialogueGroups": [],
      "TalkDialogGroupIDList": [],
      "ServerInteractVerificationIDList": []
    },
    {
      "ID": 300008,
      "PosX": 21.05,
      "PosY": -2.133955,
      "PosZ": -144.95,
      "Name": "Prop8",
      "RotY": 180.0001,
      "PropID": 105,
      "IsOverrideInitLevelGraph": true,
      "CampID": 4,
      "MapLayerID": 1,
      "CustomTriggerMap": {},
      "BridgeStateRotations": [],
      "DialogueGroups": [],
      "TalkDialogGroupIDList": [],
      "ServerInteractVerificationIDList": []
    },
    {
      "ID": 300009,
      "PosX": -5.29,
      "PosY": -2.107291,
      "PosZ": -170.316,
      "Name": "Prop9",
      "RotY": 90.0,
      "PropID": 101004,
      "IsOverrideInitLevelGraph": true,
      "ValueSource": {
        "Values": [
          {
            "$type": "SharedString",
            "Key": "Maze_Prop_Chap01_IronGate06Controller_ConfigID",
            "Value": "21,300004"
          },
          {
            "$type": "SharedString",
            "Key": "Maze_Chap01_Prop_IronGate06_LockHint",
            "Value": "MazeText_LockedDoor"
          }
        ]
      },
      "CampID": 4,
      "MapLayerID": 1,
      "CustomTriggerMap": {},
      "BridgeStateRotations": [],
      "DialogueGroups": [],
      "TalkDialogGroupIDList": [],
      "ServerInteractVerificationIDList": []
    }
  ],
  "NPCList": []
}