{
  "OnInitSequece": [],
  "OnStartSequece": [
    {
      "TaskList": [
        {
          "$type": "RPG.GameCore.SetNpcWaypath",
          "TargetType": {
            "$type": "RPG.GameCore.TargetFetchAdvNpcEx",
            "FetchType": "SingleNpcByNpcID",
            "SingleNpcID": {
              "GroupID": {
                "IsDynamic": false,
                "FixedValue": {
                  "Value": 69
                }
              },
              "GroupNpcID": {
                "IsDynamic": false,
                "FixedValue": {
                  "Value": 400001
                }
              }
            }
          },
          "UsageType": "TaskFollow"
        },
        {
          "$type": "RPG.GameCore.SetNpcStatus",
          "TargetType": {
            "$type": "RPG.GameCore.TargetFetchAdvNpcEx",
            "FetchType": "SingleNpcByNpcID",
            "SingleNpcID": {
              "GroupID": {
                "IsDynamic": false,
                "FixedValue": {
                  "Value": 69
                }
              },
              "GroupNpcID": {
                "IsDynamic": false,
                "FixedValue": {
                  "Value": 400001
                }
              }
            }
          },
          "Status": "FollowByPlayer"
        }
      ]
    },
    {
      "TaskList": [
        {
          "$type": "RPG.GameCore.WaitCustomString",
          "CustomString": {
            "Value": "Mission_2010201"
          }
        },
        {
          "$type": "RPG.GameCore.TriggerPerformance",
          "ValueSource": {},
          "PerformanceType": "D",
          "PerformanceID": 201020106
        },
        {
          "$type": "RPG.GameCore.TriggerPerformance",
          "ValueSource": {},
          "PerformanceType": "C",
          "PerformanceID": 201020107
        },
        {
          "$type": "RPG.GameCore.FinishPerformanceMission",
          "Key": "Mission_201020107"
        }
      ]
    }
  ]
}