{
  "$type": "RPG.GameCore.RtLevelGroupInfo",
  "GroupName": "Exit",
  "AreaAnchorName": "LevelArea_P40002_F40002103_G28",
  "LoadCondition": {
    "Conditions": [
      {
        "Type": "SubMission",
        "Phase": "Finish",
        "ID": 800020316
      }
    ]
  },
  "LoadSide": "Server",
  "ConflictIDList": [],
  "AnchorList": [],
  "MonsterList": [],
  "PropList": [
    {
      "PropID": 1024,
      "IsOverrideInitLevelGraph": true,
      "Trigger": {
        "Radius": 2.5,
        "PointList": []
      },
      "CampID": 4,
      "State": "Open",
      "CustomTriggerMap": {},
      "BridgeStateRotations": [],
      "DialogueGroups": [],
      "TalkDialogGroupIDList": [],
      "ServerInteractVerificationIDList": [],
      "OverrideBoardShowList": [],
      "Name": "Prop1",
      "ID": 300001,
      "PosX": -58.91287,
      "PosY": -1.055329,
      "PosZ": -50.90938
    }
  ],
  "DistrictList": [],
  "WaypointList": [],
  "PathwayList": [],
  "BattleAreaList": [],
  "NPCList": [],
  "CrowdList": [],
  "PedestrianList": []
}