{
  "OnInitSequece": [],
  "OnStartSequece": [
    {
      "TaskList": [
        {
          "$type": "RPG.GameCore.CreateProp",
          "GroupID": {
            "IsDynamic": false,
            "FixedValue": {
              "Value": 18
            }
          },
          "GroupPropID": {
            "IsDynamic": false,
            "FixedValue": {
              "Value": 300001
            }
          },
          "CreateList": []
        }
      ]
    },
    {
      "TaskList": [
        {
          "$type": "RPG.GameCore.WaitCustomString",
          "CustomString": {
            "Value": "Talk_102140105"
          }
        },
        {
          "$type": "RPG.GameCore.DestroyProp",
          "TargetType": {
            "$type": "RPG.GameCore.TargetFetchAdvPropEx"
          },
          "ID": {
            "IsDynamic": false,
            "FixedValue": {
              "Value": 300001
            }
          },
          "GroupID": {
            "IsDynamic": false,
            "FixedValue": {
              "Value": 18
            }
          },
          "DestroyList": []
        },
        {
          "$type": "RPG.GameCore.TriggerPerformance",
          "ValueSource": {},
          "PerformanceType": "PlayVideo",
          "PerformanceID": 102140106
        },
        {
          "$type": "RPG.GameCore.CreateProp",
          "GroupID": {
            "IsDynamic": false,
            "FixedValue": {
              "Value": 18
            }
          },
          "GroupPropID": {
            "IsDynamic": false,
            "FixedValue": {
              "Value": 300001
            }
          },
          "CreateList": []
        },
        {
          "$type": "RPG.GameCore.FinishPerformanceMission",
          "Key": "Mission_102140105"
        }
      ]
    }
  ]
}